ecoact_access/__init__.py
ecoact_access/db_model/__init__.py
ecoact_access/domain_model/__init__.py
ecoact_access-0.0.1.dist-info/METADATA
ecoact_access-0.0.1.dist-info/WHEEL
ecoact_access-0.0.1.dist-info/RECORD
