Metadata-Version: 2.1
Name: ecoact-access
Version: 0.0.1
Summary: Ecoact internal library for handling access
Author: Amaury Salles
Author-email: amaury.salles@se.com
Requires-Python: >=3.11,<4.0
Classifier: Programming Language :: Python :: 3
Classifier: Programming Language :: Python :: 3.11
Classifier: Programming Language :: Python :: 3.12
Requires-Dist: ecodev-core (>=0.0.25,<0.1.0)
